reschedule/__init__.py
reschedule/calendar_api.py
reschedule/config.py
reschedule/console.py
reschedule/credentials.json
reschedule/models.py
reschedule/scheduler.py
reschedule/task_parser.py
reschedule/time_helpers.py
reschedule-0.1.3.dist-info/entry_points.txt
reschedule-0.1.3.dist-info/WHEEL
reschedule-0.1.3.dist-info/METADATA
reschedule-0.1.3.dist-info/RECORD
