Metadata-Version: 2.1
Name: reschedule
Version: 0.1.3
Summary: Parser and scheduler for syncing a markdown(ish) todo list with google calendar.
Home-page: https://github.com/lukesmurray/reschedule
License: MIT
Author: Luke Murray
Author-email: lukepigeonmail@gmail.com
Requires-Python: >=3.6,<4.0
Classifier: Development Status :: 2 - Pre-Alpha
Classifier: Environment :: Console
Classifier: License :: OSI Approved :: MIT License
Classifier: Programming Language :: Python :: 3
Classifier: Programming Language :: Python :: 3.6
Classifier: Programming Language :: Python :: 3.7
Classifier: Programming Language :: Python :: 3.8
Classifier: Programming Language :: Python :: 3.9
Requires-Dist: google-api-python-client (>=1.7.11,<2.0.0)
Requires-Dist: google-auth-oauthlib (>=0.4.1,<0.5.0)
Requires-Dist: python-dateutil (>=2.8.1,<3.0.0)
Requires-Dist: tqdm (>=4.43.0,<5.0.0)
Requires-Dist: typing-extensions (>=3.7.4,<4.0.0)
Project-URL: Repository, https://github.com/lukesmurray/reschedule
